src/__init__.py
src/main.py
src/utils.py
src/config_extractor/__init__.py
src/config_extractor/extractor.py
src/github_scraper/__init__.py
src/github_scraper/readme_fetcher.py
src/llm_client/__init__.py
src/llm_client/client.py
mcp_config_extractor-0.1.8.dist-info/METADATA
mcp_config_extractor-0.1.8.dist-info/WHEEL
mcp_config_extractor-0.1.8.dist-info/entry_points.txt
mcp_config_extractor-0.1.8.dist-info/RECORD
