Metadata-Version: 2.4
Name: mcp-config-extractor
Version: 0.1.8
Summary: Extract MCP server config from GitHub repository README
Author-email: liuyoshio <liujiawei@weight-wave.com>
Requires-Python: >=3.7
Requires-Dist: openai>=1.6.1
Requires-Dist: python-dotenv>=1.0.0
Requires-Dist: requests>=2.31.0
